<annotation>
	<folder>Captures</folder>
	<filename>storage_boxes_night_north.png</filename>
	<path>C:\Users\Kent\Videos\Captures\storage_boxes_night_north.png</path>
	<source>
		<database>Unknown</database>
	</source>
	<size>
		<width>1024</width>
		<height>768</height>
		<depth>3</depth>
	</size>
	<segmented>0</segmented>
	<object>
		<name>storage_box</name>
		<pose>Unspecified</pose>
		<truncated>0</truncated>
		<difficult>0</difficult>
		<bndbox>
			<xmin>461</xmin>
			<ymin>230</ymin>
			<xmax>506</xmax>
			<ymax>290</ymax>
		</bndbox>
	</object>
	<object>
		<name>storage_box</name>
		<pose>Unspecified</pose>
		<truncated>0</truncated>
		<difficult>0</difficult>
		<bndbox>
			<xmin>239</xmin>
			<ymin>218</ymin>
			<xmax>290</xmax>
			<ymax>262</ymax>
		</bndbox>
	</object>
	<object>
		<name>storage_box</name>
		<pose>Unspecified</pose>
		<truncated>0</truncated>
		<difficult>0</difficult>
		<bndbox>
			<xmin>237</xmin>
			<ymin>261</ymin>
			<xmax>283</xmax>
			<ymax>310</ymax>
		</bndbox>
	</object>
	<object>
		<name>storage_box</name>
		<pose>Unspecified</pose>
		<truncated>0</truncated>
		<difficult>0</difficult>
		<bndbox>
			<xmin>279</xmin>
			<ymin>204</ymin>
			<xmax>334</xmax>
			<ymax>249</ymax>
		</bndbox>
	</object>
	<object>
		<name>storage_box</name>
		<pose>Unspecified</pose>
		<truncated>0</truncated>
		<difficult>0</difficult>
		<bndbox>
			<xmin>325</xmin>
			<ymin>190</ymin>
			<xmax>375</xmax>
			<ymax>231</ymax>
		</bndbox>
	</object>
	<object>
		<name>storage_box</name>
		<pose>Unspecified</pose>
		<truncated>0</truncated>
		<difficult>0</difficult>
		<bndbox>
			<xmin>251</xmin>
			<ymin>380</ymin>
			<xmax>310</xmax>
			<ymax>437</ymax>
		</bndbox>
	</object>
	<object>
		<name>storage_box</name>
		<pose>Unspecified</pose>
		<truncated>0</truncated>
		<difficult>0</difficult>
		<bndbox>
			<xmin>79</xmin>
			<ymin>301</ymin>
			<xmax>118</xmax>
			<ymax>345</ymax>
		</bndbox>
	</object>
	<object>
		<name>storage_box</name>
		<pose>Unspecified</pose>
		<truncated>0</truncated>
		<difficult>0</difficult>
		<bndbox>
			<xmin>95</xmin>
			<ymin>335</ymin>
			<xmax>143</xmax>
			<ymax>387</ymax>
		</bndbox>
	</object>
</annotation>
