<annotation>
	<folder>1024-768</folder>
	<filename>marsh-night-33.png</filename>
	<path>C:\Users\6pool\PycharmProjects\foxhole-ai\images\screens\1024-768\marsh-night-33.png</path>
	<source>
		<database>Unknown</database>
	</source>
	<size>
		<width>1024</width>
		<height>768</height>
		<depth>3</depth>
	</size>
	<segmented>0</segmented>
	<object>
		<name>truck</name>
		<pose>Unspecified</pose>
		<truncated>0</truncated>
		<difficult>0</difficult>
		<bndbox>
			<xmin>374</xmin>
			<ymin>485</ymin>
			<xmax>651</xmax>
			<ymax>706</ymax>
		</bndbox>
	</object>
	<object>
		<name>foxhole</name>
		<pose>Unspecified</pose>
		<truncated>0</truncated>
		<difficult>0</difficult>
		<bndbox>
			<xmin>74</xmin>
			<ymin>366</ymin>
			<xmax>240</xmax>
			<ymax>516</ymax>
		</bndbox>
	</object>
	<object>
		<name>pillbox</name>
		<pose>Unspecified</pose>
		<truncated>0</truncated>
		<difficult>0</difficult>
		<bndbox>
			<xmin>17</xmin>
			<ymin>311</ymin>
			<xmax>138</xmax>
			<ymax>414</ymax>
		</bndbox>
	</object>
	<object>
		<name>foxhole</name>
		<pose>Unspecified</pose>
		<truncated>0</truncated>
		<difficult>0</difficult>
		<bndbox>
			<xmin>440</xmin>
			<ymin>159</ymin>
			<xmax>572</xmax>
			<ymax>257</ymax>
		</bndbox>
	</object>
	<object>
		<name>foxhole</name>
		<pose>Unspecified</pose>
		<truncated>0</truncated>
		<difficult>0</difficult>
		<bndbox>
			<xmin>678</xmin>
			<ymin>154</ymin>
			<xmax>819</xmax>
			<ymax>256</ymax>
		</bndbox>
	</object>
	<object>
		<name>sandbag</name>
		<pose>Unspecified</pose>
		<truncated>0</truncated>
		<difficult>0</difficult>
		<bndbox>
			<xmin>512</xmin>
			<ymin>83</ymin>
			<xmax>606</xmax>
			<ymax>160</ymax>
		</bndbox>
	</object>
	<object>
		<name>sandbag</name>
		<pose>Unspecified</pose>
		<truncated>0</truncated>
		<difficult>0</difficult>
		<bndbox>
			<xmin>606</xmin>
			<ymin>78</ymin>
			<xmax>695</xmax>
			<ymax>130</ymax>
		</bndbox>
	</object>
	<object>
		<name>sandbag</name>
		<pose>Unspecified</pose>
		<truncated>0</truncated>
		<difficult>0</difficult>
		<bndbox>
			<xmin>689</xmin>
			<ymin>106</ymin>
			<xmax>777</xmax>
			<ymax>146</ymax>
		</bndbox>
	</object>
	<object>
		<name>sandbag</name>
		<pose>Unspecified</pose>
		<truncated>0</truncated>
		<difficult>0</difficult>
		<bndbox>
			<xmin>776</xmin>
			<ymin>121</ymin>
			<xmax>871</xmax>
			<ymax>170</ymax>
		</bndbox>
	</object>
	<object>
		<name>foxhole</name>
		<pose>Unspecified</pose>
		<truncated>1</truncated>
		<difficult>0</difficult>
		<bndbox>
			<xmin>711</xmin>
			<ymin>1</ymin>
			<xmax>836</xmax>
			<ymax>84</ymax>
		</bndbox>
	</object>
	<object>
		<name>foxhole</name>
		<pose>Unspecified</pose>
		<truncated>0</truncated>
		<difficult>0</difficult>
		<bndbox>
			<xmin>679</xmin>
			<ymin>426</ymin>
			<xmax>848</xmax>
			<ymax>553</ymax>
		</bndbox>
	</object>
	<object>
		<name>foxhole</name>
		<pose>Unspecified</pose>
		<truncated>1</truncated>
		<difficult>0</difficult>
		<bndbox>
			<xmin>273</xmin>
			<ymin>1</ymin>
			<xmax>378</xmax>
			<ymax>77</ymax>
		</bndbox>
	</object>
	<object>
		<name>player</name>
		<pose>Unspecified</pose>
		<truncated>0</truncated>
		<difficult>0</difficult>
		<bndbox>
			<xmin>456</xmin>
			<ymin>405</ymin>
			<xmax>484</xmax>
			<ymax>447</ymax>
		</bndbox>
	</object>
</annotation>
